akiraPyYaml/__init__.py
akiraPyYaml/functions.py
akiraPyYaml-1.0.11.dist-info/LICENSE
akiraPyYaml-1.0.11.dist-info/METADATA
akiraPyYaml-1.0.11.dist-info/WHEEL
akiraPyYaml-1.0.11.dist-info/top_level.txt
akiraPyYaml-1.0.11.dist-info/RECORD
