Metadata-Version: 2.1
Name: akiraPyYaml
Version: 1.0.11
Summary: Library for interacting with files and data in yaml format
Home-page: https://github.com/toshuomj
Author: Marc Jose Rubio
Author-email: joserubiomarc@gmail.com
License: MIT
Platform: UNKNOWN
License-File: LICENSE
Requires-Dist: pyyaml
